otl/__init__.py
otl/__version__.py
otl/base/__init__.py
otl/base/test.py
otl/db/__init__.py
otl/db/mysql.py
otl/db/common/SQL.py
otl/db/common/__init__.py
otl/dingtalk/__init__.py
otl/dingtalk/dingtalk_api.py
otl/email/__init__.py
otl/email/email_api.py
otl/wechat/__init__.py
otl/wechat/wechat_api.py
otl/wechat/src/AbstractApi.py
otl/wechat/src/CoreApi.py
otl/wechat/src/__init__.py
otl-1.10.2.dist-info/LICENSE
otl-1.10.2.dist-info/METADATA
otl-1.10.2.dist-info/WHEEL
otl-1.10.2.dist-info/top_level.txt
otl-1.10.2.dist-info/RECORD
