Metadata-Version: 2.1
Name: otl
Version: 1.10.2
Summary: 运维工具集
Home-page: https://github.com/xuyonggit/otl.git
Author: xuyong
Author-email: xuyong@qq.com
License: MIT
Classifier: Programming Language :: Python :: 3
Classifier: License :: OSI Approved :: MIT License
Classifier: Operating System :: OS Independent
License-File: LICENSE
Requires-Dist: PyMySQL (==1.0.2)
Requires-Dist: DBUtils (==3.0.2)
Requires-Dist: requests (==2.28.0)
